fit2sm/__init__.py
fit2sm/_version.py
fit2sm/dcgm.py
fit2sm/fit2sm.py
fit2sm/motifs.py
fit2sm/ubcm.py
fit2sm-0.1.0.dist-info/licenses/LICENSE
fit2sm-0.1.0.dist-info/METADATA
fit2sm-0.1.0.dist-info/WHEEL
fit2sm-0.1.0.dist-info/top_level.txt
fit2sm-0.1.0.dist-info/RECORD
