Metadata-Version: 2.4
Name: fit2SM
Version: 0.1.0
Summary: Python package for fitting a mean-field fitness-based two-star model (Fit2SM) for undirected binary networks (dcGM and UBCM are also available for comparisons).
Author: Mattia Marzi
License-Expression: MIT
Project-URL: Homepage, https://github.com/mattiamarzi/fit2SM
Project-URL: Repository, https://github.com/mattiamarzi/fit2SM
Project-URL: Issues, https://github.com/mattiamarzi/fit2SM/issues
Requires-Python: >=3.10
License-File: LICENSE
Requires-Dist: numpy>=1.23
Requires-Dist: scipy>=1.10
Requires-Dist: numba>=0.57
Provides-Extra: dev
Requires-Dist: pytest>=7.0; extra == "dev"
Requires-Dist: pytest-cov>=5.0; extra == "dev"
Requires-Dist: coverage>=7.6.1; extra == "dev"
Requires-Dist: ruff>=0.4.0; extra == "dev"
Requires-Dist: black>=24.0; extra == "dev"
Requires-Dist: pre-commit>=3.0; extra == "dev"
Dynamic: license-file
